rudalle_paddle/__init__.py
rudalle_paddle/future.py
rudalle_paddle/image_prompts.py
rudalle_paddle/pipelines.py
rudalle_paddle/tokenizer.py
rudalle_paddle/utils.py
rudalle_paddle/dalle/__init__.py
rudalle_paddle/dalle/fp16.py
rudalle_paddle/dalle/image_attention.py
rudalle_paddle/dalle/model.py
rudalle_paddle/dalle/transformer.py
rudalle_paddle/dalle/utils.py
rudalle_paddle/packages/__init__.py
rudalle_paddle/packages/einops/__init__.py
rudalle_paddle/packages/einops/_backends.py
rudalle_paddle/packages/einops/_torch_specific.py
rudalle_paddle/packages/einops/einops.py
rudalle_paddle/packages/einops/parsing.py
rudalle_paddle/packages/einops/layers/__init__.py
rudalle_paddle/packages/einops/layers/_weighted_einsum.py
rudalle_paddle/packages/einops/layers/chainer.py
rudalle_paddle/packages/einops/layers/gluon.py
rudalle_paddle/packages/einops/layers/keras.py
rudalle_paddle/packages/einops/layers/paddle.py
rudalle_paddle/packages/einops/layers/tensorflow.py
rudalle_paddle/packages/einops/layers/torch.py
rudalle_paddle/packages/taming/modules/diffusionmodules/model.py
rudalle_paddle/packages/transformers/__init__.py
rudalle_paddle/realesrgan/__init__.py
rudalle_paddle/realesrgan/arch_util.py
rudalle_paddle/realesrgan/model.py
rudalle_paddle/realesrgan/rrdbnet_arch.py
rudalle_paddle/realesrgan/utils.py
rudalle_paddle/ruclip/__init__.py
rudalle_paddle/ruclip/model.py
rudalle_paddle/ruclip/processor.py
rudalle_paddle/vae/__init__.py
rudalle_paddle/vae/model.py
rudalle_paddle/vae/vqgan.gumbelf8-sber.config.yml
rudalle_paddle-0.0.1rc1.dist-info/LICENSE.txt
rudalle_paddle-0.0.1rc1.dist-info/METADATA
rudalle_paddle-0.0.1rc1.dist-info/WHEEL
rudalle_paddle-0.0.1rc1.dist-info/top_level.txt
rudalle_paddle-0.0.1rc1.dist-info/RECORD
