Metadata-Version: 2.1
Name: rudalle-paddle
Version: 0.0.1rc1
Summary: UNKNOWN
Home-page: UNKNOWN
Author: SberAI, SberDevices
Author-email: 
License: UNKNOWN
Platform: UNKNOWN
License-File: LICENSE.txt
Requires-Dist: more-itertools (~=8.10.0)
Requires-Dist: youtokentome (~=1.0.6)
Requires-Dist: omegaconf (>=2.0.0)
Requires-Dist: paddlepaddle-gpu (~=2.2.0)
Requires-Dist: paddleclip
Requires-Dist: huggingface-hub (~=0.1.2)
Requires-Dist: matplotlib
